brain/__init__.py
brain_lang-0.1.0.dist-info/METADATA
brain_lang-0.1.0.dist-info/WHEEL
brain_lang-0.1.0.dist-info/RECORD
